{
  "form_id": "FM-PB-009",
  "generated_by": "tools/derive_field_guidance.py",
  "note": "Per-field fill-value guidance (value type, required-ness, choice-group conditionals). Derived offline from schema/mapping/constraints; consistent with the fill engine. Not legal advice — verify against the official form before filing. Currency/time guidance is conservative because the printed '$'/AM-PM are not read here.",
  "value_types": [
    "address",
    "bar_number",
    "case_number",
    "checkbox",
    "city",
    "county",
    "court_location",
    "currency",
    "date",
    "docket",
    "email",
    "free_text",
    "organization_name",
    "percent",
    "person_name",
    "phone",
    "signature",
    "state",
    "time",
    "zip"
  ],
  "fields": {
    "check_box3": {
      "value_type": "free_text",
      "required": false,
      "guidance": "Free-form narrative text specific to the situation."
    },
    "plaintiff": {
      "value_type": "person_name",
      "required": true,
      "guidance": "A person's name (the engine collapses to initials only if it overflows the box)."
    },
    "location_town": {
      "value_type": "court_location",
      "required": false,
      "guidance": "The court division / town where the case is filed."
    },
    "docket_no": {
      "value_type": "docket",
      "required": false,
      "guidance": "The docket number (e.g. CV-2024-0099)."
    },
    "defendant": {
      "value_type": "person_name",
      "required": true,
      "guidance": "A person's name (the engine collapses to initials only if it overflows the box)."
    },
    "in_re": {
      "value_type": "free_text",
      "required": false,
      "guidance": "Free-form narrative text specific to the situation."
    },
    "undefined_2": {
      "value_type": "free_text",
      "required": false,
      "guidance": "Free-form narrative text specific to the situation."
    },
    "i": {
      "value_type": "person_name",
      "required": true,
      "guidance": "A person's name (the engine collapses to initials only if it overflows the box)."
    },
    "true_to_the_best_of_my_knowledge_and_belief_1": {
      "value_type": "free_text",
      "required": false,
      "guidance": "Free-form narrative text specific to the situation."
    },
    "true_to_the_best_of_my_knowledge_and_belief_2": {
      "value_type": "free_text",
      "required": false,
      "guidance": "Free-form narrative text specific to the situation."
    },
    "true_to_the_best_of_my_knowledge_and_belief_3": {
      "value_type": "free_text",
      "required": false,
      "guidance": "Free-form narrative text specific to the situation."
    },
    "true_to_the_best_of_my_knowledge_and_belief_4": {
      "value_type": "free_text",
      "required": false,
      "guidance": "Free-form narrative text specific to the situation."
    },
    "true_to_the_best_of_my_knowledge_and_belief_5": {
      "value_type": "free_text",
      "required": false,
      "guidance": "Free-form narrative text specific to the situation."
    },
    "true_to_the_best_of_my_knowledge_and_belief_6": {
      "value_type": "free_text",
      "required": false,
      "guidance": "Free-form narrative text specific to the situation."
    },
    "true_to_the_best_of_my_knowledge_and_belief_7": {
      "value_type": "free_text",
      "required": false,
      "guidance": "Free-form narrative text specific to the situation."
    },
    "true_to_the_best_of_my_knowledge_and_belief_8": {
      "value_type": "free_text",
      "required": false,
      "guidance": "Free-form narrative text specific to the situation."
    },
    "true_to_the_best_of_my_knowledge_and_belief_9": {
      "value_type": "free_text",
      "required": false,
      "guidance": "Free-form narrative text specific to the situation."
    },
    "true_to_the_best_of_my_knowledge_and_belief_10": {
      "value_type": "free_text",
      "required": false,
      "guidance": "Free-form narrative text specific to the situation."
    },
    "true_to_the_best_of_my_knowledge_and_belief_11": {
      "value_type": "free_text",
      "required": false,
      "guidance": "Free-form narrative text specific to the situation."
    },
    "true_to_the_best_of_my_knowledge_and_belief_12": {
      "value_type": "free_text",
      "required": false,
      "guidance": "Free-form narrative text specific to the situation."
    },
    "true_to_the_best_of_my_knowledge_and_belief_13": {
      "value_type": "free_text",
      "required": false,
      "guidance": "Free-form narrative text specific to the situation."
    },
    "true_to_the_best_of_my_knowledge_and_belief_14": {
      "value_type": "free_text",
      "required": false,
      "guidance": "Free-form narrative text specific to the situation."
    },
    "true_to_the_best_of_my_knowledge_and_belief_15": {
      "value_type": "free_text",
      "required": false,
      "guidance": "Free-form narrative text specific to the situation."
    },
    "true_to_the_best_of_my_knowledge_and_belief_16": {
      "value_type": "free_text",
      "required": false,
      "guidance": "Free-form narrative text specific to the situation."
    },
    "true_to_the_best_of_my_knowledge_and_belief_17": {
      "value_type": "free_text",
      "required": false,
      "guidance": "Free-form narrative text specific to the situation."
    },
    "true_to_the_best_of_my_knowledge_and_belief_18": {
      "value_type": "free_text",
      "required": false,
      "guidance": "Free-form narrative text specific to the situation."
    },
    "true_to_the_best_of_my_knowledge_and_belief_19": {
      "value_type": "free_text",
      "required": false,
      "guidance": "Free-form narrative text specific to the situation."
    },
    "statements_are_made_for_use_as_evidence_in_court_and_that_i_am_subject_to_prosecution_for_perjury_punishable_by": {
      "value_type": "free_text",
      "required": false,
      "guidance": "Free-form narrative text specific to the situation."
    },
    "date_mmddyyyy": {
      "value_type": "date",
      "format": "us_slash",
      "required": false,
      "guidance": "A calendar date."
    },
    "undefined_3": {
      "value_type": "free_text",
      "required": false,
      "guidance": "Free-form narrative text specific to the situation."
    }
  }
}
