{
  "form_id": "CV-060",
  "schema_version": "0.3",
  "source_pdf": "pdfs/CV-060.pdf",
  "artifact_pdf": "form.pdf",
  "n_pages": 1,
  "n_fields": 25,
  "by_category": {
    "party_attr": 3,
    "narrative_derived": 19,
    "case_constant": 3
  },
  "_skill_metadata_override": {},
  "fields": [
    {
      "field_id": "plaintiff",
      "widget_id": "W001",
      "label": "Plaintiff",
      "type": "text",
      "data_type": "text",
      "page": 0,
      "rect": [
        31,
        61,
        234,
        74
      ],
      "category": "party_attr",
      "subcategory": "plaintiff",
      "party": "plaintiff"
    },
    {
      "field_id": "superior_court",
      "widget_id": "W002",
      "label": "Superior Court",
      "type": "text",
      "data_type": "text",
      "page": 0,
      "rect": [
        356,
        75,
        369,
        88
      ],
      "category": "narrative_derived",
      "subcategory": "free_text",
      "party": null
    },
    {
      "field_id": "district_court",
      "widget_id": "W003",
      "label": "District Court",
      "type": "text",
      "data_type": "text",
      "page": 0,
      "rect": [
        450,
        75,
        463,
        88
      ],
      "category": "narrative_derived",
      "subcategory": "free_text",
      "party": null
    },
    {
      "field_id": "county",
      "widget_id": "W004",
      "label": "County",
      "type": "text",
      "data_type": "text",
      "page": 0,
      "rect": [
        396,
        88,
        581,
        102
      ],
      "category": "case_constant",
      "subcategory": "county",
      "party": null
    },
    {
      "field_id": "location_town",
      "widget_id": "W005",
      "label": "Location Town",
      "type": "text",
      "data_type": "text",
      "page": 0,
      "rect": [
        440,
        103,
        581,
        117
      ],
      "category": "case_constant",
      "subcategory": "county",
      "party": null
    },
    {
      "field_id": "defendant",
      "widget_id": "W006",
      "label": "Defendant",
      "type": "text",
      "data_type": "text",
      "page": 0,
      "rect": [
        31,
        120,
        234,
        133
      ],
      "category": "party_attr",
      "subcategory": "defendant",
      "party": "defendant"
    },
    {
      "field_id": "docket_no",
      "widget_id": "W007",
      "label": "Docket No",
      "type": "text",
      "data_type": "text",
      "page": 0,
      "rect": [
        415,
        118,
        581,
        131
      ],
      "category": "case_constant",
      "subcategory": "docket_no",
      "party": null
    },
    {
      "field_id": "to",
      "widget_id": "W008",
      "label": "TO",
      "type": "text",
      "data_type": "text",
      "page": 0,
      "rect": [
        56,
        206,
        576,
        220
      ],
      "category": "narrative_derived",
      "subcategory": "free_text",
      "party": null
    },
    {
      "field_id": "justice_superior_court",
      "widget_id": "W009",
      "label": "Justice Superior Court",
      "type": "text",
      "data_type": "text",
      "page": 0,
      "rect": [
        59,
        222,
        72,
        235
      ],
      "category": "narrative_derived",
      "subcategory": "free_text",
      "party": null
    },
    {
      "field_id": "judge_district_court_of_the_state_of_maine",
      "widget_id": "W010",
      "label": "Judge District Court of the State of Maine",
      "type": "text",
      "data_type": "text",
      "page": 0,
      "rect": [
        189,
        222,
        202,
        235
      ],
      "category": "narrative_derived",
      "subcategory": "free_text",
      "party": null
    },
    {
      "field_id": "i_respectfully_ask_for_the_approval_of_the_court_to_withdraw_the_sum_of",
      "widget_id": "W011",
      "label": "I respectfully ask for the approval of the Court to withdraw the sum of",
      "type": "text",
      "data_type": "text",
      "page": 0,
      "rect": [
        409,
        250,
        507,
        264
      ],
      "category": "narrative_derived",
      "subcategory": "free_text",
      "party": null
    },
    {
      "field_id": "no",
      "widget_id": "W012",
      "label": "No",
      "type": "text",
      "data_type": "text",
      "page": 0,
      "rect": [
        56,
        265,
        288,
        278
      ],
      "category": "narrative_derived",
      "subcategory": "free_text",
      "party": null
    },
    {
      "field_id": "in_the_name_of",
      "widget_id": "W013",
      "label": "in the name of",
      "type": "text",
      "data_type": "text",
      "page": 0,
      "rect": [
        365,
        265,
        576,
        278
      ],
      "category": "narrative_derived",
      "subcategory": "free_text",
      "party": null
    },
    {
      "field_id": "now_in_the_financial_institution_of_1",
      "widget_id": "W014",
      "label": "now in the Financial Institution of 1",
      "type": "text",
      "data_type": "text",
      "page": 0,
      "rect": [
        202,
        279,
        565,
        293
      ],
      "category": "narrative_derived",
      "subcategory": "free_text",
      "party": null
    },
    {
      "field_id": "for_the_following_reasons",
      "widget_id": "W015",
      "label": "for the following reasons",
      "type": "text",
      "data_type": "text",
      "page": 0,
      "rect": [
        36,
        294,
        288,
        308
      ],
      "category": "narrative_derived",
      "subcategory": "free_text",
      "party": null
    },
    {
      "field_id": "now_in_the_financial_institution_of_2",
      "widget_id": "W016",
      "label": "now in the Financial Institution of 2",
      "type": "text",
      "data_type": "text",
      "page": 0,
      "rect": [
        36,
        309,
        576,
        322
      ],
      "category": "narrative_derived",
      "subcategory": "free_text",
      "party": null
    },
    {
      "field_id": "1",
      "widget_id": "W017",
      "label": "1",
      "type": "text",
      "data_type": "text",
      "page": 0,
      "rect": [
        36,
        323,
        576,
        337
      ],
      "category": "narrative_derived",
      "subcategory": "free_text",
      "party": null
    },
    {
      "field_id": "now_in_the_financial_institution_of_3",
      "widget_id": "W018",
      "label": "now in the Financial Institution of 3",
      "type": "text",
      "data_type": "text",
      "page": 0,
      "rect": [
        36,
        338,
        576,
        352
      ],
      "category": "narrative_derived",
      "subcategory": "free_text",
      "party": null
    },
    {
      "field_id": "2",
      "widget_id": "W019",
      "label": "2",
      "type": "text",
      "data_type": "text",
      "page": 0,
      "rect": [
        36,
        353,
        576,
        366
      ],
      "category": "narrative_derived",
      "subcategory": "free_text",
      "party": null
    },
    {
      "field_id": "now_in_the_financial_institution_of_4",
      "widget_id": "W020",
      "label": "now in the Financial Institution of 4",
      "type": "text",
      "data_type": "text",
      "page": 0,
      "rect": [
        36,
        367,
        576,
        381
      ],
      "category": "narrative_derived",
      "subcategory": "free_text",
      "party": null
    },
    {
      "field_id": "3",
      "widget_id": "W021",
      "label": "3",
      "type": "text",
      "data_type": "text",
      "page": 0,
      "rect": [
        36,
        382,
        576,
        396
      ],
      "category": "narrative_derived",
      "subcategory": "free_text",
      "party": null
    },
    {
      "field_id": "date_mmddyyyy",
      "widget_id": "W022",
      "label": "Date mmddyyyy",
      "type": "text",
      "data_type": "text",
      "page": 0,
      "rect": [
        143,
        411,
        252,
        424
      ],
      "category": "narrative_derived",
      "subcategory": "date",
      "party": null
    },
    {
      "field_id": "undefined",
      "widget_id": "W023",
      "label": "undefined",
      "type": "text",
      "data_type": "text",
      "page": 0,
      "rect": [
        324,
        411,
        576,
        424
      ],
      "category": "narrative_derived",
      "subcategory": "free_text",
      "party": null
    },
    {
      "field_id": "next_friend",
      "widget_id": "W024",
      "label": "Next Friend",
      "type": "text",
      "data_type": "text",
      "page": 0,
      "rect": [
        333,
        425,
        346,
        438
      ],
      "category": "narrative_derived",
      "subcategory": "free_text",
      "party": null
    },
    {
      "field_id": "petitioner",
      "widget_id": "W025",
      "label": "Petitioner",
      "type": "text",
      "data_type": "text",
      "page": 0,
      "rect": [
        412,
        425,
        425,
        438
      ],
      "category": "party_attr",
      "subcategory": "petitioner",
      "party": "petitioner"
    }
  ]
}
