{
  "matter": {
    "docket_number": "FM-2024-00000",
    "court_county": "Cumberland",
    "court_location": "Portland",
    "court_type": "District Court",
    "case_type": "family_matters",
    "filing_date": "2024-03-15"
  },
  "parties": {
    "plaintiff": {
      "full_name": "Jane Q. Doe",
      "address": "123 Main Street",
      "city": "Portland",
      "state": "ME",
      "zip": "04101",
      "phone": "207-555-0101",
      "email": "jane.doe@example.com",
      "date_of_birth": "1985-01-15"
    },
    "defendant": {
      "full_name": "John R. Roe",
      "address": "456 Oak Avenue",
      "city": "Portland",
      "state": "ME",
      "zip": "04101",
      "phone": "207-555-0102",
      "email": "john.roe@example.com",
      "date_of_birth": "1983-06-20"
    },
    "attorney": {
      "full_name": "Pat L. Lawyer, Esq.",
      "bar_number": "ME-000000",
      "address": "1 Court Plaza, Suite 100",
      "city": "Portland",
      "state": "ME",
      "zip": "04101",
      "phone": "207-555-0150",
      "email": "attorney@example.com"
    },
    "child_1": {
      "full_name": "Sam Doe",
      "date_of_birth": "2015-04-10",
      "address": "123 Main Street",
      "city": "Portland",
      "state": "ME",
      "zip": "04101"
    },
    "child_2": {
      "full_name": "Alex Doe",
      "date_of_birth": "2018-09-05",
      "address": "123 Main Street",
      "city": "Portland",
      "state": "ME",
      "zip": "04101"
    }
  },
  "party": {
    "full_name": "Jane Q. Doe",
    "address": "123 Main Street",
    "city": "Portland",
    "state": "ME",
    "zip": "04101",
    "phone": "207-555-0101",
    "email": "jane.doe@example.com",
    "date_of_birth": "1985-01-15",
    "signature": "Jane Q. Doe"
  },
  "facts": {
    "marriage_date": "2012-06-30",
    "separation_date": "2023-11-01",
    "grounds": "Irreconcilable Differences",
    "issues": [
      "Division of Marital Assets",
      "Child Custody",
      "Child Support",
      "Spousal Support"
    ],
    "summary": "Sample fact pattern for testing form fills. All names, contacts, dates, and amounts here are fictitious placeholders (Doe/Roe, example.com, 555 phone range).",
    "community_service_address": "789 Pine Street",
    "community_service_address_2": "Portland, ME 04101",
    "community_service_comments": [
      "Sample comment (fictional) for testing this form's fill."
    ],
    "community_service_completion_date": "2024-06-30",
    "community_service_hours": "20",
    "community_service_hours_total": "20",
    "community_service_log": [
      [
        "04/01/2024",
        "4"
      ],
      [
        "04/08/2024",
        "4"
      ]
    ],
    "community_service_org": "Acme Example Community Org",
    "community_service_phone": "207-555-0199",
    "community_service_rating": "satisfactory",
    "community_service_supervisor": "Riley T. Sample",
    "community_service_supervisor_phone": "207-555-0198",
    "juvenile_doc_office": "Example Regional Office (fictional)",
    "juvenile_gender": "female",
    "juvenile_gender_text": "female",
    "jv017_before_judge": true,
    "jv040_discharge_other_than_class_abc": true,
    "jv040_filer": "Riley T. Sample, JCCO (fictional)",
    "jv043_attorney_address": "1 Court Plaza, Suite 100",
    "jv043_attorney_csz": "Portland, ME 04101",
    "jv043_attorney_email": "attorney@example.com",
    "jv043_attorney_phone": "207-555-0150",
    "jv043_filing_attorney": "Pat L. Lawyer, Esq.",
    "jv044_attorney": "Pat L. Lawyer, Esq.",
    "jv044_attorney_address": "1 Court Plaza, Suite 100",
    "jv044_attorney_bar": "ME-000000",
    "jv044_attorney_city": "Portland",
    "jv044_attorney_email": "attorney@example.com",
    "jv044_attorney_phone": "207-555-0150",
    "jv044_attorney_zip": "04101",
    "jv044_seal_reasons": "Sample sealing reasons (fictional) for testing this form's fill.",
    "jv_appointment_date": "2024-04-01",
    "jv_custody_location": "Example Youth Center (fictional)",
    "jv_evaluation_program": "Example Evaluation Program (fictional)",
    "jv_hearing_date": "2024-04-15",
    "jv_signer_role": "parent",
    "jv_state_attorney_bar": "ME-000000",
    "jv_state_attorney_name": "Casey L. Sample",
    "notice_text": "Sample notice text (fictional) for testing this form's fill."
  }
}
